<content-type>
  <display-name>Infobox</display-name>
  <super-type>base:unstructured</super-type>
  <form>
    <input type="TextLine" name="heading">
      <label>Overskrift</label>
      <occurrences minimum="0" maximum="1"/>
    </input>
    <input type="TextArea" name="preface">
      <label>Ingress</label>
      <occurrences minimum="0" maximum="1"/>
    </input>
    <input type="HtmlArea" name="description">
      <label>Description</label>
      <occurrences minimum="0" maximum="1"/>
    </input>
  </form>
</content-type>